{
  "events": [
    {
      "year": "1798",
      "description": "Constantine Hangerli arrives in Bucharest, Wallachia, as its new Prince, invested by the Ottoman Empire.",
      "html": "<li>\n<a href=\"/wiki/1798\" title=\"1798\">1798</a> – <a href=\"/wiki/Constantine_Hangerli\" title=\"Constantine Hangerli\">Constantine Hangerli</a> arrives in <a href=\"/wiki/Bucharest\" title=\"Bucharest\">Bucharest</a>, <a href=\"/wiki/Wallachia\" title=\"Wallachia\">Wallachia</a>, as its new <a href=\"/wiki/Prince_of_Wallachia\" class=\"mw-redirect\" title=\"Prince of Wallachia\">Prince</a>, invested by the <a href=\"/wiki/Ottoman_Empire\" title=\"Ottoman Empire\">Ottoman Empire</a>.<sup id=\"cite_ref-7\" class=\"reference\"><a href=\"#cite_note-7\"><span class=\"cite-bracket\">[</span>7<span class=\"cite-bracket\">]</span></a></sup>\n</li>",
      "entities": [
        {
          "name": "Constantine Hangerli",
          "url": "/wiki/Constantine_Hangerli",
          "length": 10653
        },
        {
          "name": "Bucharest",
          "url": "/wiki/Bucharest",
          "length": 154755
        },
        {
          "name": "Wallachia",
          "url": "/wiki/Wallachia",
          "length": 69480
        },
        {
          "name": "Prince of Wallachia",
          "url": "/wiki/Prince_of_Wallachia",
          "length": 42
        },
        {
          "name": "Ottoman Empire",
          "url": "/wiki/Ottoman_Empire",
          "length": 268337
        }
      ]
    },
    {
      "year": "1903",
      "description": "Topsy, an elephant, is electrocuted by the owners of Luna Park, Coney Island. The Edison film company records the film Electrocuting an Elephant of Topsy's death.",
      "html": "<li>\n<a href=\"/wiki/1903\" title=\"1903\">1903</a> – <a href=\"/wiki/Topsy_(elephant)\" title=\"Topsy (elephant)\">Topsy</a>, an <a href=\"/wiki/Elephant\" title=\"Elephant\">elephant</a>, is electrocuted by the owners of <a href=\"/wiki/Luna_Park,_Coney_Island_(1903)\" class=\"mw-redirect\" title=\"Luna Park, Coney Island (1903)\">Luna Park, Coney Island</a>. The <a href=\"/wiki/Edison_Studios\" title=\"Edison Studios\">Edison film company</a> records the film <i><a href=\"/wiki/Electrocuting_an_Elephant\" title=\"Electrocuting an Elephant\">Electrocuting an Elephant</a></i> of Topsy's death.<sup id=\"cite_ref-17\" class=\"reference\"><a href=\"#cite_note-17\"><span class=\"cite-bracket\">[</span>17<span class=\"cite-bracket\">]</span></a></sup>\n</li>",
      "entities": [
        {
          "name": "Topsy (elephant)",
          "url": "/wiki/Topsy_(elephant)",
          "length": 31915
        },
        {
          "name": "Elephant",
          "url": "/wiki/Elephant",
          "length": 135477
        },
        {
          "name": "Luna Park, Coney Island (1903)",
          "url": "/wiki/Luna_Park,_Coney_Island_(1903)",
          "length": 61
        },
        {
          "name": "Edison Studios",
          "url": "/wiki/Edison_Studios",
          "length": 13367
        },
        {
          "name": "Electrocuting an Elephant",
          "url": "/wiki/Electrocuting_an_Elephant",
          "length": 9850
        }
      ]
    },
    {
      "year": "1976",
      "description": "The Troubles: The Ulster Volunteer Force shoots dead six Irish Catholic civilians in County Armagh, Northern Ireland. The next day, gunmen would shoot dead ten Protestant civilians nearby in retaliation.",
      "html": "<li>\n<a href=\"/wiki/1976\" title=\"1976\">1976</a> – <a href=\"/wiki/The_Troubles\" title=\"The Troubles\">The Troubles</a>: The <a href=\"/wiki/Ulster_Volunteer_Force\" title=\"Ulster Volunteer Force\">Ulster Volunteer Force</a> <a href=\"/wiki/Reavey_and_O%27Dowd_killings\" title=\"Reavey and O'Dowd killings\">shoots dead six Irish Catholic civilians</a> in <a href=\"/wiki/County_Armagh\" title=\"County Armagh\">County Armagh</a>, Northern Ireland. The next day, gunmen <a href=\"/wiki/Kingsmill_massacre\" title=\"Kingsmill massacre\">would shoot dead ten Protestant civilians</a> nearby in retaliation.<sup id=\"cite_ref-31\" class=\"reference\"><a href=\"#cite_note-31\"><span class=\"cite-bracket\">[</span>31<span class=\"cite-bracket\">]</span></a></sup>\n</li>",
      "entities": [
        {
          "name": "The Troubles",
          "url": "/wiki/The_Troubles",
          "length": 218680
        },
        {
          "name": "Ulster Volunteer Force",
          "url": "/wiki/Ulster_Volunteer_Force",
          "length": 107459
        },
        {
          "name": "Reavey and O'Dowd killings",
          "url": "/wiki/Reavey_and_O%27Dowd_killings",
          "length": 23704
        },
        {
          "name": "County Armagh",
          "url": "/wiki/County_Armagh",
          "length": 39750
        },
        {
          "name": "Kingsmill massacre",
          "url": "/wiki/Kingsmill_massacre",
          "length": 52760
        }
      ]
    },
    {
      "year": "1987",
      "description": "The Maryland train collision: An Amtrak train en route to Boston from Washington, D.C., collides with Conrail engines in Chase, Maryland, United States, killing 16 people.",
      "html": "<li>\n<a href=\"/wiki/1987\" title=\"1987\">1987</a> – The <a href=\"/wiki/1987_Maryland_train_collision\" title=\"1987 Maryland train collision\">Maryland train collision</a>: An <a href=\"/wiki/Amtrak\" title=\"Amtrak\">Amtrak</a> train <i>en route</i> to <a href=\"/wiki/Boston\" title=\"Boston\">Boston</a> from Washington, D.C., collides with <a href=\"/wiki/Conrail\" title=\"Conrail\">Conrail</a> engines in <a href=\"/wiki/Chase,_Maryland\" title=\"Chase, Maryland\">Chase, Maryland</a>, United States, killing 16 people.<sup id=\"cite_ref-32\" class=\"reference\"><a href=\"#cite_note-32\"><span class=\"cite-bracket\">[</span>32<span class=\"cite-bracket\">]</span></a></sup>\n</li>",
      "entities": [
        {
          "name": "1987 Maryland train collision",
          "url": "/wiki/1987_Maryland_train_collision",
          "length": 28746
        },
        {
          "name": "Amtrak",
          "url": "/wiki/Amtrak",
          "length": 160305
        },
        {
          "name": "Boston",
          "url": "/wiki/Boston",
          "length": 227117
        },
        {
          "name": "Conrail",
          "url": "/wiki/Conrail",
          "length": 51214
        },
        {
          "name": "Chase, Maryland",
          "url": "/wiki/Chase,_Maryland",
          "length": 9674
        }
      ]
    },
    {
      "year": "2004",
      "description": "Spirit, a NASA Mars rover, lands successfully on Mars at 04:35 UTC.",
      "html": "<li>\n<a href=\"/wiki/2004\" title=\"2004\">2004</a> – <a href=\"/wiki/Spirit_(rover)\" title=\"Spirit (rover)\"><i>Spirit</i></a>, a <a href=\"/wiki/NASA\" title=\"NASA\">NASA</a> <a href=\"/wiki/Mars_rover\" title=\"Mars rover\">Mars rover</a>, lands successfully on <a href=\"/wiki/Mars\" title=\"Mars\">Mars</a> at 04:35 <a href=\"/wiki/Coordinated_Universal_Time\" title=\"Coordinated Universal Time\">UTC</a>.<sup id=\"cite_ref-38\" class=\"reference\"><a href=\"#cite_note-38\"><span class=\"cite-bracket\">[</span>38<span class=\"cite-bracket\">]</span></a></sup>\n</li>",
      "entities": [
        {
          "name": "Spirit (rover)",
          "url": "/wiki/Spirit_(rover)",
          "length": 52761
        },
        {
          "name": "NASA",
          "url": "/wiki/NASA",
          "length": 228390
        },
        {
          "name": "Mars rover",
          "url": "/wiki/Mars_rover",
          "length": 28335
        },
        {
          "name": "Mars",
          "url": "/wiki/Mars",
          "length": 210834
        },
        {
          "name": "Coordinated Universal Time",
          "url": "/wiki/Coordinated_Universal_Time",
          "length": 53364
        }
      ]
    },
    {
      "year": "46 BC",
      "description": "Julius Caesar fights Titus Labienus in the Battle of Ruspina.",
      "html": "<li>\n<a href=\"/wiki/46_BC\" title=\"46 BC\">46 BC</a> – <a href=\"/wiki/Julius_Caesar\" title=\"Julius Caesar\">Julius Caesar</a> fights <a href=\"/wiki/Titus_Labienus\" title=\"Titus Labienus\">Titus Labienus</a> in the <a href=\"/wiki/Battle_of_Ruspina\" title=\"Battle of Ruspina\">Battle of Ruspina</a>.<sup id=\"cite_ref-1\" class=\"reference\"><a href=\"#cite_note-1\"><span class=\"cite-bracket\">[</span>1<span class=\"cite-bracket\">]</span></a></sup>\n</li>",
      "entities": [
        {
          "name": "46 BC",
          "url": "/wiki/46_BC",
          "length": 6295
        },
        {
          "name": "Julius Caesar",
          "url": "/wiki/Julius_Caesar",
          "length": 143346
        },
        {
          "name": "Titus Labienus",
          "url": "/wiki/Titus_Labienus",
          "length": 14250
        },
        {
          "name": "Battle of Ruspina",
          "url": "/wiki/Battle_of_Ruspina",
          "length": 8461
        }
      ]
    },
    {
      "year": "1986",
      "description": "James Milner, English footballer, was born.",
      "html": "<li>1986 – <a href=\"/wiki/James_Milner\" title=\"James Milner\">James Milner</a>, English footballer<sup id=\"cite_ref-181\" class=\"reference\"><a href=\"#cite_note-181\"><span class=\"cite-bracket\">[</span>181<span class=\"cite-bracket\">]</span></a></sup>\n</li>",
      "entities": [
        {
          "name": "James Milner",
          "url": "/wiki/James_Milner",
          "length": 148602
        }
      ]
    },
    {
      "year": "1941",
      "description": "Henri Bergson, French philosopher and academic, Nobel Prize laureate, died.",
      "html": "<li>\n<a href=\"/wiki/1941\" title=\"1941\">1941</a> – <a href=\"/wiki/Henri_Bergson\" title=\"Henri Bergson\">Henri Bergson</a>, French philosopher and academic, <a href=\"/wiki/Nobel_Prize_in_Literature\" title=\"Nobel Prize in Literature\">Nobel Prize</a> laureate (b. 1859)<sup id=\"cite_ref-244\" class=\"reference\"><a href=\"#cite_note-244\"><span class=\"cite-bracket\">[</span>244<span class=\"cite-bracket\">]</span></a></sup>\n</li>",
      "entities": [
        {
          "name": "Henri Bergson",
          "url": "/wiki/Henri_Bergson",
          "length": 86549
        },
        {
          "name": "Nobel Prize in Literature",
          "url": "/wiki/Nobel_Prize_in_Literature",
          "length": 78775
        }
      ]
    }
  ],
  "births": [
    {
      "year": "1986",
      "description": "James Milner, English footballer, was born.",
      "html": "<li>1986 – <a href=\"/wiki/James_Milner\" title=\"James Milner\">James Milner</a>, English footballer<sup id=\"cite_ref-181\" class=\"reference\"><a href=\"#cite_note-181\"><span class=\"cite-bracket\">[</span>181<span class=\"cite-bracket\">]</span></a></sup>\n</li>",
      "entities": [
        {
          "name": "James Milner",
          "url": "/wiki/James_Milner",
          "length": 148602
        }
      ]
    },
    {
      "year": "1994",
      "description": "Derrick Henry, American football player, was born.",
      "html": "<li>\n<a href=\"/wiki/1994\" title=\"1994\">1994</a> – <a href=\"/wiki/Derrick_Henry\" title=\"Derrick Henry\">Derrick Henry</a>, American football player<sup id=\"cite_ref-195\" class=\"reference\"><a href=\"#cite_note-195\"><span class=\"cite-bracket\">[</span>195<span class=\"cite-bracket\">]</span></a></sup>\n</li>",
      "entities": [
        {
          "name": "Derrick Henry",
          "url": "/wiki/Derrick_Henry",
          "length": 139464
        }
      ]
    },
    {
      "year": "1990",
      "description": "Toni Kroos, German footballer, was born.",
      "html": "<li>1990 – <a href=\"/wiki/Toni_Kroos\" title=\"Toni Kroos\">Toni Kroos</a>, German footballer<sup id=\"cite_ref-190\" class=\"reference\"><a href=\"#cite_note-190\"><span class=\"cite-bracket\">[</span>190<span class=\"cite-bracket\">]</span></a></sup>\n</li>",
      "entities": [
        {
          "name": "Toni Kroos",
          "url": "/wiki/Toni_Kroos",
          "length": 135349
        }
      ]
    }
  ],
  "deaths": [
    {
      "year": "1965",
      "description": "T. S. Eliot, American-English poet, playwright, and critic, Nobel Prize laureate, died.",
      "html": "<li>\n<a href=\"/wiki/1965\" title=\"1965\">1965</a> – <a href=\"/wiki/T._S._Eliot\" title=\"T. S. Eliot\">T. S. Eliot</a>, American-English poet, playwright, and critic, <a href=\"/wiki/Nobel_Prize_in_Literature\" title=\"Nobel Prize in Literature\">Nobel Prize</a> laureate (b. 1888)<sup id=\"cite_ref-250\" class=\"reference\"><a href=\"#cite_note-250\"><span class=\"cite-bracket\">[</span>250<span class=\"cite-bracket\">]</span></a></sup>\n</li>",
      "entities": [
        {
          "name": "T. S. Eliot",
          "url": "/wiki/T._S._Eliot",
          "length": 100481
        },
        {
          "name": "Nobel Prize in Literature",
          "url": "/wiki/Nobel_Prize_in_Literature",
          "length": 78775
        }
      ]
    },
    {
      "year": "2024",
      "description": "Glynis Johns, British actress and singer, died.",
      "html": "<li>\n<a href=\"/wiki/2024\" title=\"2024\">2024</a> – <a href=\"/wiki/Glynis_Johns\" title=\"Glynis Johns\">Glynis Johns</a>, British actress and singer (b. 1923)<sup id=\"cite_ref-299\" class=\"reference\"><a href=\"#cite_note-299\"><span class=\"cite-bracket\">[</span>299<span class=\"cite-bracket\">]</span></a></sup>\n</li>",
      "entities": [
        {
          "name": "Glynis Johns",
          "url": "/wiki/Glynis_Johns",
          "length": 96340
        }
      ]
    },
    {
      "year": "1941",
      "description": "Henri Bergson, French philosopher and academic, Nobel Prize laureate, died.",
      "html": "<li>\n<a href=\"/wiki/1941\" title=\"1941\">1941</a> – <a href=\"/wiki/Henri_Bergson\" title=\"Henri Bergson\">Henri Bergson</a>, French philosopher and academic, <a href=\"/wiki/Nobel_Prize_in_Literature\" title=\"Nobel Prize in Literature\">Nobel Prize</a> laureate (b. 1859)<sup id=\"cite_ref-244\" class=\"reference\"><a href=\"#cite_note-244\"><span class=\"cite-bracket\">[</span>244<span class=\"cite-bracket\">]</span></a></sup>\n</li>",
      "entities": [
        {
          "name": "Henri Bergson",
          "url": "/wiki/Henri_Bergson",
          "length": 86549
        },
        {
          "name": "Nobel Prize in Literature",
          "url": "/wiki/Nobel_Prize_in_Literature",
          "length": 78775
        }
      ]
    }
  ]
}