{
  "events": [
    {
      "year": "38 BC",
      "description": "Octavian divorces his wife Scribonia and marries Livia Drusilla, ending the fragile peace between the Second Triumvirate and Sextus Pompey.",
      "html": "<li>\n<a href=\"/wiki/38_BC\" title=\"38 BC\">38 BC</a> – <a href=\"/wiki/Octavian\" class=\"mw-redirect\" title=\"Octavian\">Octavian</a> divorces his wife <a href=\"/wiki/Scribonia_(wife_of_Augustus)\" class=\"mw-redirect\" title=\"Scribonia (wife of Augustus)\">Scribonia</a> and marries <a href=\"/wiki/Livia_Drusilla\" class=\"mw-redirect\" title=\"Livia Drusilla\">Livia Drusilla</a>, ending the fragile peace between the <a href=\"/wiki/Second_Triumvirate\" title=\"Second Triumvirate\">Second Triumvirate</a> and <a href=\"/wiki/Sextus_Pompey\" title=\"Sextus Pompey\">Sextus Pompey</a>.<sup id=\"cite_ref-1\" class=\"reference\"><a href=\"#cite_note-1\"><span class=\"cite-bracket\">[</span>1<span class=\"cite-bracket\">]</span></a></sup>\n</li>",
      "entities": [
        {
          "name": "38 BC",
          "url": "/wiki/38_BC",
          "length": 2720
        },
        {
          "name": "Octavian",
          "url": "/wiki/Octavian",
          "length": 22
        },
        {
          "name": "Scribonia (wife of Augustus)",
          "url": "/wiki/Scribonia_(wife_of_Augustus)",
          "length": 59
        },
        {
          "name": "Livia Drusilla",
          "url": "/wiki/Livia_Drusilla",
          "length": 19
        },
        {
          "name": "Second Triumvirate",
          "url": "/wiki/Second_Triumvirate",
          "length": 55327
        },
        {
          "name": "Sextus Pompey",
          "url": "/wiki/Sextus_Pompey",
          "length": 14800
        }
      ]
    },
    {
      "year": "1915",
      "description": "Russia defeats Ottoman Turkey in the Battle of Sarikamish during the Caucasus Campaign of World War I.",
      "html": "<li>\n<a href=\"/wiki/1915\" title=\"1915\">1915</a> – <a href=\"/wiki/Russia\" title=\"Russia\">Russia</a> defeats <a href=\"/wiki/Ottoman_Empire\" title=\"Ottoman Empire\">Ottoman Turkey</a> in the <a href=\"/wiki/Battle_of_Sarikamish\" title=\"Battle of Sarikamish\">Battle of Sarikamish</a> during the <a href=\"/wiki/Caucasus_Campaign\" class=\"mw-redirect\" title=\"Caucasus Campaign\">Caucasus Campaign</a> of <a href=\"/wiki/World_War_I\" title=\"World War I\">World War I</a>.</li>",
      "entities": [
        {
          "name": "Russia",
          "url": "/wiki/Russia",
          "length": 381726
        },
        {
          "name": "Ottoman Empire",
          "url": "/wiki/Ottoman_Empire",
          "length": 268337
        },
        {
          "name": "Battle of Sarikamish",
          "url": "/wiki/Battle_of_Sarikamish",
          "length": 71527
        },
        {
          "name": "Caucasus Campaign",
          "url": "/wiki/Caucasus_Campaign",
          "length": 48
        },
        {
          "name": "World War I",
          "url": "/wiki/World_War_I",
          "length": 213543
        }
      ]
    },
    {
      "year": "2013",
      "description": "Shahzad Luqman is murdered by members of Golden Dawn in Petralona, Athens, leading the creation of new measures to combat race-based attacks in Greece.",
      "html": "<li>\n<a href=\"/wiki/2013\" title=\"2013\">2013</a> – Shahzad Luqman is <a href=\"/wiki/Murder_of_Shahzad_Luqman\" title=\"Murder of Shahzad Luqman\">murdered</a> by members of <a href=\"/wiki/Golden_Dawn_(Greece)\" title=\"Golden Dawn (Greece)\">Golden Dawn</a> in <a href=\"/wiki/Petralona\" title=\"Petralona\">Petralona</a>, <a href=\"/wiki/Athens\" title=\"Athens\">Athens</a>, leading the creation of new measures to combat race-based attacks in <a href=\"/wiki/Greece\" title=\"Greece\">Greece</a>.<sup id=\"cite_ref-21\" class=\"reference\"><a href=\"#cite_note-21\"><span class=\"cite-bracket\">[</span>21<span class=\"cite-bracket\">]</span></a></sup>\n</li>",
      "entities": [
        {
          "name": "Murder of Shahzad Luqman",
          "url": "/wiki/Murder_of_Shahzad_Luqman",
          "length": 7147
        },
        {
          "name": "Golden Dawn (Greece)",
          "url": "/wiki/Golden_Dawn_(Greece)",
          "length": 142762
        },
        {
          "name": "Petralona",
          "url": "/wiki/Petralona",
          "length": 3636
        },
        {
          "name": "Athens",
          "url": "/wiki/Athens",
          "length": 137081
        },
        {
          "name": "Greece",
          "url": "/wiki/Greece",
          "length": 292640
        }
      ]
    },
    {
      "year": "1781",
      "description": "American Revolutionary War: Battle of Cowpens: Continental troops under Brigadier General Daniel Morgan defeat British forces under Lieutenant Colonel Banastre Tarleton at the battle in South Carolina.",
      "html": "<li>\n<a href=\"/wiki/1781\" title=\"1781\">1781</a> – <a href=\"/wiki/American_Revolutionary_War\" title=\"American Revolutionary War\">American Revolutionary War</a>: <a href=\"/wiki/Battle_of_Cowpens\" title=\"Battle of Cowpens\">Battle of Cowpens</a>: Continental troops under Brigadier General <a href=\"/wiki/Daniel_Morgan\" title=\"Daniel Morgan\">Daniel Morgan</a> defeat British forces under Lieutenant Colonel <a href=\"/wiki/Banastre_Tarleton\" title=\"Banastre Tarleton\">Banastre Tarleton</a> at the battle in <a href=\"/wiki/South_Carolina\" title=\"South Carolina\">South Carolina</a>.</li>",
      "entities": [
        {
          "name": "American Revolutionary War",
          "url": "/wiki/American_Revolutionary_War",
          "length": 285512
        },
        {
          "name": "Battle of Cowpens",
          "url": "/wiki/Battle_of_Cowpens",
          "length": 48709
        },
        {
          "name": "Daniel Morgan",
          "url": "/wiki/Daniel_Morgan",
          "length": 37129
        },
        {
          "name": "Banastre Tarleton",
          "url": "/wiki/Banastre_Tarleton",
          "length": 64689
        },
        {
          "name": "South Carolina",
          "url": "/wiki/South_Carolina",
          "length": 130953
        }
      ]
    },
    {
      "year": "1998",
      "description": "Clinton–Lewinsky scandal: Matt Drudge breaks the story of the Bill Clinton–Monica Lewinsky affair on his Drudge Report website.",
      "html": "<li>\n<a href=\"/wiki/1998\" title=\"1998\">1998</a> – <a href=\"/wiki/Clinton%E2%80%93Lewinsky_scandal\" title=\"Clinton–Lewinsky scandal\">Clinton–Lewinsky scandal</a>: <a href=\"/wiki/Matt_Drudge\" title=\"Matt Drudge\">Matt Drudge</a> breaks the story of the <a href=\"/wiki/Bill_Clinton\" title=\"Bill Clinton\">Bill Clinton</a>–<a href=\"/wiki/Monica_Lewinsky\" title=\"Monica Lewinsky\">Monica Lewinsky</a> affair on his <i><a href=\"/wiki/Drudge_Report\" title=\"Drudge Report\">Drudge Report</a></i> website.</li>",
      "entities": [
        {
          "name": "Clinton–Lewinsky scandal",
          "url": "/wiki/Clinton%E2%80%93Lewinsky_scandal",
          "length": 39393
        },
        {
          "name": "Matt Drudge",
          "url": "/wiki/Matt_Drudge",
          "length": 25907
        },
        {
          "name": "Bill Clinton",
          "url": "/wiki/Bill_Clinton",
          "length": 271452
        },
        {
          "name": "Monica Lewinsky",
          "url": "/wiki/Monica_Lewinsky",
          "length": 57020
        },
        {
          "name": "Drudge Report",
          "url": "/wiki/Drudge_Report",
          "length": 72708
        }
      ]
    },
    {
      "year": "1649",
      "description": "The Second Ormonde Peace creates an alliance between the Irish Royalists and Confederates during the War of the Three Kingdoms. The coalition was then decisively defeated during the Cromwellian conquest of Ireland.",
      "html": "<li>\n<a href=\"/wiki/1649\" title=\"1649\">1649</a> – The <a href=\"/wiki/Second_Ormonde_Peace\" title=\"Second Ormonde Peace\">Second Ormonde Peace</a> creates an alliance between the <a href=\"/wiki/Cavaliers\" class=\"mw-redirect\" title=\"Cavaliers\">Irish Royalists</a> and <a href=\"/wiki/Irish_Confederates\" class=\"mw-redirect\" title=\"Irish Confederates\">Confederates</a> during the <a href=\"/wiki/War_of_the_Three_Kingdoms\" class=\"mw-redirect\" title=\"War of the Three Kingdoms\">War of the Three Kingdoms</a>. The coalition was then decisively defeated during the <a href=\"/wiki/Cromwellian_conquest_of_Ireland\" title=\"Cromwellian conquest of Ireland\">Cromwellian conquest of Ireland</a>.<sup id=\"cite_ref-10\" class=\"reference\"><a href=\"#cite_note-10\"><span class=\"cite-bracket\">[</span>10<span class=\"cite-bracket\">]</span></a></sup>\n</li>",
      "entities": [
        {
          "name": "Second Ormonde Peace",
          "url": "/wiki/Second_Ormonde_Peace",
          "length": 6280
        },
        {
          "name": "Cavaliers",
          "url": "/wiki/Cavaliers",
          "length": 71
        },
        {
          "name": "Irish Confederates",
          "url": "/wiki/Irish_Confederates",
          "length": 32
        },
        {
          "name": "War of the Three Kingdoms",
          "url": "/wiki/War_of_the_Three_Kingdoms",
          "length": 40
        },
        {
          "name": "Cromwellian conquest of Ireland",
          "url": "/wiki/Cromwellian_conquest_of_Ireland",
          "length": 43999
        }
      ]
    },
    {
      "year": "1942",
      "description": "Muhammad Ali, American boxer and activist, was born.",
      "html": "<li>\n<a href=\"/wiki/1942\" title=\"1942\">1942</a> – <a href=\"/wiki/Muhammad_Ali\" title=\"Muhammad Ali\">Muhammad Ali</a>, American boxer and activist (d. 2016)<sup id=\"cite_ref-44\" class=\"reference\"><a href=\"#cite_note-44\"><span class=\"cite-bracket\">[</span>44<span class=\"cite-bracket\">]</span></a></sup>\n</li>",
      "entities": [
        {
          "name": "Muhammad Ali",
          "url": "/wiki/Muhammad_Ali",
          "length": 296471
        }
      ]
    },
    {
      "year": "2010",
      "description": "Jyoti Basu, Indian politician and 9th Chief Minister of West Bengal, died.",
      "html": "<li>2010   – <a href=\"/wiki/Jyoti_Basu\" title=\"Jyoti Basu\">Jyoti Basu</a>, Indian politician and 9th <a href=\"/wiki/Chief_Minister_of_West_Bengal\" class=\"mw-redirect\" title=\"Chief Minister of West Bengal\">Chief Minister of West Bengal</a> (b. 1914)</li>",
      "entities": [
        {
          "name": "Jyoti Basu",
          "url": "/wiki/Jyoti_Basu",
          "length": 172355
        },
        {
          "name": "Chief Minister of West Bengal",
          "url": "/wiki/Chief_Minister_of_West_Bengal",
          "length": 52
        }
      ]
    }
  ],
  "births": [
    {
      "year": "1942",
      "description": "Muhammad Ali, American boxer and activist, was born.",
      "html": "<li>\n<a href=\"/wiki/1942\" title=\"1942\">1942</a> – <a href=\"/wiki/Muhammad_Ali\" title=\"Muhammad Ali\">Muhammad Ali</a>, American boxer and activist (d. 2016)<sup id=\"cite_ref-44\" class=\"reference\"><a href=\"#cite_note-44\"><span class=\"cite-bracket\">[</span>44<span class=\"cite-bracket\">]</span></a></sup>\n</li>",
      "entities": [
        {
          "name": "Muhammad Ali",
          "url": "/wiki/Muhammad_Ali",
          "length": 296471
        }
      ]
    },
    {
      "year": "1871",
      "description": "Nicolae Iorga, Romanian historian and politician, 34th Prime Minister of Romania, was born.",
      "html": "<li>1871   – <a href=\"/wiki/Nicolae_Iorga\" title=\"Nicolae Iorga\">Nicolae Iorga</a>, Romanian historian and politician, 34th <a href=\"/wiki/Prime_Minister_of_Romania\" title=\"Prime Minister of Romania\">Prime Minister of Romania</a> (d. 1940)</li>",
      "entities": [
        {
          "name": "Nicolae Iorga",
          "url": "/wiki/Nicolae_Iorga",
          "length": 234820
        },
        {
          "name": "Prime Minister of Romania",
          "url": "/wiki/Prime_Minister_of_Romania",
          "length": 18337
        }
      ]
    },
    {
      "year": "1706",
      "description": "Benjamin Franklin, American publisher, inventor, and politician, 6th President of Pennsylvania, was born.",
      "html": "<li>\n<a href=\"/wiki/1706\" title=\"1706\">1706</a> – <a href=\"/wiki/Benjamin_Franklin\" title=\"Benjamin Franklin\">Benjamin Franklin</a>, American publisher, inventor, and politician, 6th <a href=\"/wiki/List_of_Governors_of_Pennsylvania\" class=\"mw-redirect\" title=\"List of Governors of Pennsylvania\">President of Pennsylvania</a> (d. 1790)</li>",
      "entities": [
        {
          "name": "Benjamin Franklin",
          "url": "/wiki/Benjamin_Franklin",
          "length": 216369
        },
        {
          "name": "List of Governors of Pennsylvania",
          "url": "/wiki/List_of_Governors_of_Pennsylvania",
          "length": 64
        }
      ]
    }
  ],
  "deaths": [
    {
      "year": "2008",
      "description": "Bobby Fischer, American chess player and author, died.",
      "html": "<li>\n<a href=\"/wiki/2008\" title=\"2008\">2008</a> – <a href=\"/wiki/Bobby_Fischer\" title=\"Bobby Fischer\">Bobby Fischer</a>, American chess player and author (b. 1943)<sup id=\"cite_ref-77\" class=\"reference\"><a href=\"#cite_note-77\"><span class=\"cite-bracket\">[</span>77<span class=\"cite-bracket\">]</span></a></sup>\n</li>",
      "entities": [
        {
          "name": "Bobby Fischer",
          "url": "/wiki/Bobby_Fischer",
          "length": 230616
        }
      ]
    },
    {
      "year": "2010",
      "description": "Jyoti Basu, Indian politician and 9th Chief Minister of West Bengal, died.",
      "html": "<li>2010   – <a href=\"/wiki/Jyoti_Basu\" title=\"Jyoti Basu\">Jyoti Basu</a>, Indian politician and 9th <a href=\"/wiki/Chief_Minister_of_West_Bengal\" class=\"mw-redirect\" title=\"Chief Minister of West Bengal\">Chief Minister of West Bengal</a> (b. 1914)</li>",
      "entities": [
        {
          "name": "Jyoti Basu",
          "url": "/wiki/Jyoti_Basu",
          "length": 172355
        },
        {
          "name": "Chief Minister of West Bengal",
          "url": "/wiki/Chief_Minister_of_West_Bengal",
          "length": 52
        }
      ]
    },
    {
      "year": "1468",
      "description": "Skanderbeg, Albanian soldier and politician, died.",
      "html": "<li>\n<a href=\"/wiki/1468\" title=\"1468\">1468</a> – <a href=\"/wiki/Skanderbeg\" title=\"Skanderbeg\">Skanderbeg</a>, Albanian soldier and politician (b. 1405)</li>",
      "entities": [
        {
          "name": "Skanderbeg",
          "url": "/wiki/Skanderbeg",
          "length": 146275
        }
      ]
    }
  ]
}